odoo_backup/__init__.py
odoo_backup/cli.py
obx-0.4.2.dist-info/METADATA
obx-0.4.2.dist-info/WHEEL
obx-0.4.2.dist-info/entry_points.txt
obx-0.4.2.dist-info/licenses/LICENSE
obx-0.4.2.dist-info/RECORD
