Metadata-Version: 2.4
Name: obx
Version: 0.4.2
Summary: Interactive Odoo backup tool for databases and filestore
Project-URL: Homepage, https://github.com/sotoplatero/odoo-backup-tool
Project-URL: Repository, https://github.com/sotoplatero/odoo-backup-tool
Project-URL: Issues, https://github.com/sotoplatero/odoo-backup-tool/issues
Project-URL: Documentation, https://github.com/sotoplatero/odoo-backup-tool#readme
Project-URL: Changelog, https://github.com/sotoplatero/odoo-backup-tool/blob/main/CHANGELOG.md
Author-email: Soto Platero <soto.platero@gmail.com>
License-File: LICENSE
Keywords: backup,cli,database,odoo,postgresql
Classifier: Development Status :: 4 - Beta
Classifier: Intended Audience :: Developers
Classifier: Intended Audience :: System Administrators
Classifier: License :: OSI Approved :: MIT License
Classifier: Operating System :: OS Independent
Classifier: Programming Language :: Python :: 3
Classifier: Programming Language :: Python :: 3.8
Classifier: Programming Language :: Python :: 3.9
Classifier: Programming Language :: Python :: 3.10
Classifier: Programming Language :: Python :: 3.11
Classifier: Programming Language :: Python :: 3.12
Classifier: Programming Language :: Python :: 3.13
Classifier: Topic :: Database
Classifier: Topic :: System :: Archiving :: Backup
Classifier: Topic :: System :: Systems Administration
Requires-Python: >=3.8
Requires-Dist: click>=8.0.0
Requires-Dist: psycopg2-binary>=2.9.0
Requires-Dist: rich>=13.0.0
